AUTHORS.rst
CONTRIBUTING.rst
HISTORY.rst
LICENSE
MANIFEST.in
README.rst
setup.cfg
setup.py
docs/Makefile
docs/authors.rst
docs/conf.py
docs/contributing.rst
docs/history.rst
docs/index.rst
docs/installation.rst
docs/make.bat
docs/modules.rst
docs/racpy.rst
docs/readme.rst
docs/usage.rst
docs/_build/html/_static/file.png
docs/_build/html/_static/minus.png
docs/_build/html/_static/plus.png
racpy/__init__.py
racpy/cli.py
racpy/core.py
racpy/exceptions.py
racpy/makeplot.py
racpy.egg-info/PKG-INFO
racpy.egg-info/SOURCES.txt
racpy.egg-info/dependency_links.txt
racpy.egg-info/entry_points.txt
racpy.egg-info/not-zip-safe
racpy.egg-info/requires.txt
racpy.egg-info/top_level.txt
tests/__init__.py
tests/test_func.py
tests/test_racpy.py