Metadata-Version: 1.2
Name: racpy
Version: 0.1.4
Summary: RNASeq Age Calculation in Python
Home-page: https://github.com/reese3928/racpy
Author: Xu Ren, Pei Fen Kuan
Author-email: xuren2120@gmail.com, peifen.kuan@stonybrook.edu
License: MIT license
Keywords: racpy
Platform: UNKNOWN
Classifier: Development Status :: 2 - Pre-Alpha
Classifier: Intended Audience :: Developers
Classifier: License :: OSI Approved :: MIT License
Classifier: Natural Language :: English
Classifier: Programming Language :: Python :: 3
Classifier: Programming Language :: Python :: 3.5
Classifier: Programming Language :: Python :: 3.6
Classifier: Programming Language :: Python :: 3.7
Classifier: Programming Language :: Python :: 3.8
Requires-Python: >=3.5
